so_ml_tools/__init__.py
so_ml_tools/data/__init__.py
so_ml_tools/data/image.py
so_ml_tools/data/loader.py
so_ml_tools/data/normalize.py
so_ml_tools/data/plot.py
so_ml_tools/data/split.py
so_ml_tools/evaluate/__init__.py
so_ml_tools/evaluate/analyze.py
so_ml_tools/evaluate/classification.py
so_ml_tools/evaluate/plot.py
so_ml_tools/imblearn/__init__.py
so_ml_tools/imblearn/smote.py
so_ml_tools/nlp/__init__.py
so_ml_tools/nlp/text.py
so_ml_tools/nlp/embedding/__init__.py
so_ml_tools/nlp/embedding/export.py
so_ml_tools/pd/__init__.py
so_ml_tools/pd/dataframe.py
so_ml_tools/pd/plot.py
so_ml_tools/pd/report.py
so_ml_tools/pd/series.py
so_ml_tools/regression/__init__.py
so_ml_tools/regression/feature_importance.py
so_ml_tools/shap/__init__.py
so_ml_tools/shap/report.py
so_ml_tools/sklearn/__init__.py
so_ml_tools/sklearn/encoder.py
so_ml_tools/sklearn/imputer.py
so_ml_tools/tf/__init__.py
so_ml_tools/tf/augment.py
so_ml_tools/tf/dataset.py
so_ml_tools/tf/mixed_precision.py
so_ml_tools/tf/tensor.py
so_ml_tools/tf/tensorboard.py
so_ml_tools/tf/fit/__init__.py
so_ml_tools/tf/fit/callback.py
so_ml_tools/tf/loss/__init__.py
so_ml_tools/tf/loss/mase.py
so_ml_tools/tf/model/__init__.py
so_ml_tools/tf/model/inspect.py
so_ml_tools/tf/model/io.py
so_ml_tools/tf/model/layer.py
so_ml_tools/tf/model/plot.py
so_ml_tools/tf/model/predict.py
so_ml_tools/timeseries/__init__.py
so_ml_tools/timeseries/data.py
so_ml_tools/timeseries/plot.py
so_ml_tools/util/__init__.py
so_ml_tools/util/io.py
so_ml_tools/util/label.py
so_ml_tools/util/onehot.py
so_ml_tools/util/prediction.py
so_ml_tools/util/random.py
so_ml_tools/util/types.py
so_ml_tools-0.1.214.dist-info/METADATA
so_ml_tools-0.1.214.dist-info/WHEEL
so_ml_tools-0.1.214.dist-info/top_level.txt
so_ml_tools-0.1.214.dist-info/RECORD
