Metadata-Version: 2.1
Name: so-ml-tools
Version: 0.1.214
Summary: Utilities library for TensorFlow
Home-page: UNKNOWN
Author: Ronald Mathies
License: UNKNOWN
Keywords: python,machine,deep,learning,tensorflow
Platform: UNKNOWN
Classifier: Programming Language :: Python :: 3
Requires-Dist: matplotlib ==3.7.2
Requires-Dist: pandas ==2.0.3
Requires-Dist: numpy ==1.24.3
Requires-Dist: scikit-learn ==1.3.0
Requires-Dist: tensorflow ==2.13.1
Requires-Dist: scipy ==1.10.1
Requires-Dist: shap ==0.42.1
Requires-Dist: imbalanced-learn ==0.11.0
Requires-Dist: sweetviz ==2.3.1
Requires-Dist: seaborn ==0.12.2
Requires-Dist: nltk ==3.8.1
